render_engine_parser/__init__.py
render_engine_parser/base_parsers.py
render_engine_parser-2024.9.0.dist-info/LICENSE
render_engine_parser-2024.9.0.dist-info/METADATA
render_engine_parser-2024.9.0.dist-info/WHEEL
render_engine_parser-2024.9.0.dist-info/top_level.txt
render_engine_parser-2024.9.0.dist-info/RECORD
