Metadata-Version: 2.1
Name: render_engine_parser
Version: 2024.9.0
Summary: Parser System for Render Engine
Project-URL: homepage, https://github.com/kjaymiller/render_engine/
Project-URL: repository, https://github.com/kjaymiller/render_engine/
Project-URL: documentation, https://render-engine.readthedocs.io/en/latest/
Requires-Python: >=3.10
License-File: LICENSE
Requires-Dist: python-frontmatter
Provides-Extra: dev
Requires-Dist: pytest; extra == "dev"
Requires-Dist: pytest-cov; extra == "dev"
Requires-Dist: ruff; extra == "dev"
